pyttsx4/__init__.py
pyttsx4/driver.py
pyttsx4/engine.py
pyttsx4/voice.py
pyttsx4/drivers/__init__.py
pyttsx4/drivers/_espeak.py
pyttsx4/drivers/coqui_ai_tts.py
pyttsx4/drivers/dummy.py
pyttsx4/drivers/espeak.py
pyttsx4/drivers/nsss.py
pyttsx4/drivers/sapi5.py
pyttsx4-3.0.14.dist-info/LICENSE
pyttsx4-3.0.14.dist-info/METADATA
pyttsx4-3.0.14.dist-info/WHEEL
pyttsx4-3.0.14.dist-info/top_level.txt
pyttsx4-3.0.14.dist-info/RECORD
