Metadata-Version: 2.1
Name: pyttsx4
Version: 3.0.14
Summary: Text to Speech (TTS) library for Python 3. Works without internet connection or delay. Supports multiple TTS engines, including Sapi5, nsss, and espeak.
Home-page: https://github.com/Jiangshan00001/pyttsx4
Author: Natesh M Bhat
Author-email: 710806594@qq.com
License: UNKNOWN
Keywords: pyttsx,ivona,pyttsx for python3,TTS for python3,pyttsx4,text to speech for python,tts,text to speech,speech,speech synthesis,offline text to speech,offline tts,gtts
Platform: UNKNOWN
Classifier: Intended Audience :: End Users/Desktop
Classifier: Intended Audience :: Developers
Classifier: Intended Audience :: Information Technology
Classifier: Intended Audience :: System Administrators
Classifier: Operating System :: MacOS :: MacOS X
Classifier: Operating System :: Microsoft :: Windows
Classifier: Operating System :: POSIX
Classifier: License :: OSI Approved :: Mozilla Public License 2.0 (MPL 2.0)
Classifier: Programming Language :: Python :: 3
Classifier: Programming Language :: Python :: 3.5
Classifier: Programming Language :: Python :: 3.6
Classifier: Programming Language :: Python :: 3.7
Classifier: Programming Language :: Python :: 3.8
Classifier: Programming Language :: Python :: 3.9
Classifier: Programming Language :: Python :: 3.10
Classifier: Programming Language :: Python :: 3.11
Requires-Dist: six
Requires-Dist: pyobjc (>=2.4) ; platform_system == "Darwin"
Requires-Dist: comtypes ; platform_system == "Windows"
Requires-Dist: pypiwin32 ; platform_system == "Windows"
Requires-Dist: pywin32 ; platform_system == "Windows"
